dashboard/__init__.py
dashboard/auth_middleware.py
dashboard/database.py
dashboard/logger_service.py
dashboard/logs/instance_1.log
dashboard/logs/instance_8.log
dashboard/logs/instance_9.log
dashboard/main.py
dashboard/market.json
dashboard/market_data/binance_BTC_USDT_1h.csv
dashboard/market_data/okx_BTC-USDT-SWAP_1h.csv
dashboard/models.py
dashboard/notifications.py
dashboard/routers/__init__.py
dashboard/routers/api_management.py
dashboard/routers/dashboard.py
dashboard/routers/data.py
dashboard/routers/developer.py
dashboard/routers/docker.py
dashboard/routers/files.py
dashboard/routers/instances.py
dashboard/routers/market.py
dashboard/routers/notifications.py
dashboard/routers/projects.py
dashboard/routers/settings.py
dashboard/security.py
dashboard/shared.py
dashboard/static/css/custom.css
dashboard/static/css/developer_ide.css
dashboard/static/js/codemirror.js
dashboard/static/js/developer_ide.js
dashboard/static/js/lang-python.js
dashboard/temp_configs/inst_1_config.json
dashboard/temp_configs/inst_1_config.py
dashboard/temp_configs/inst_8_config.py
dashboard/temp_configs/inst_9_config.py
dashboard/templates/_api_keys_table.html
dashboard/templates/_backtest_helper.html
dashboard/templates/_backtest_history.html
dashboard/templates/_backtest_item.html
dashboard/templates/_backtest_runner.html
dashboard/templates/_dashboard_stats.html
dashboard/templates/_data_file_options.html
dashboard/templates/_data_file_select.html
dashboard/templates/_data_files_table.html
dashboard/templates/_docker_status.html
dashboard/templates/_file_browser.html
dashboard/templates/_instance_log_selector.html
dashboard/templates/_live_instance_item.html
dashboard/templates/_live_instances_list.html
dashboard/templates/_logging_and_notifications.html
dashboard/templates/_message_logs_table.html
dashboard/templates/_notification_channels_table.html
dashboard/templates/_notification_history_table.html
dashboard/templates/_notification_logs_table.html
qpanel-0.1.0.dist-info/METADATA
qpanel-0.1.0.dist-info/WHEEL
qpanel-0.1.0.dist-info/entry_points.txt
qpanel-0.1.0.dist-info/RECORD
